tracking_graph/__init__.py
tracking_graph/graphs_tools.py
tracking_graph/leicolors.py
tracking_graph/linking_models.py
tracking_graph/spikeinterface_addons.py
tracking_graph/user_api.py
tracking_graph/utils.py
tracking_graph-0.9.0.dist-info/LICENSE
tracking_graph-0.9.0.dist-info/METADATA
tracking_graph-0.9.0.dist-info/WHEEL
tracking_graph-0.9.0.dist-info/entry_points.txt
tracking_graph-0.9.0.dist-info/RECORD
