Metadata-Version: 2.1
Name: tracking_graph
Version: 0.9.0
Summary: Algorithm to track clusters across recordings
License: MIT
Author: Fernando Julian Chaure
Author-email: fchaure@fi.uba.ar
Requires-Python: >=3.10,<4.0
Classifier: License :: OSI Approved :: MIT License
Classifier: Programming Language :: Python :: 3
Classifier: Programming Language :: Python :: 3.10
Classifier: Programming Language :: Python :: 3.11
Classifier: Programming Language :: Python :: 3.12
Requires-Dist: h5py (>=3.11.0,<4.0.0)
Requires-Dist: matplotlib (>=3.9.1,<4.0.0)
Requires-Dist: networkx (>=3.3,<4.0)
Requires-Dist: numpy (>=2.0.1,<3.0.0)
Requires-Dist: spikeinterface (==0.100)
Requires-Dist: streamlit (>=1.37.0,<2.0.0)
Requires-Dist: streamlit-echarts (>=0.4.0,<0.5.0)
